aspired/__init__.py
aspired/extraction.py
aspired/flux_calibration.py
aspired/image_reduction.py
aspired/line_spread_function.py
aspired/onedspec.py
aspired/spectral_reduction.py
aspired/spectrum_oneD.py
aspired/standard_list.py
aspired/twodspec.py
aspired/util.py
aspired/wavelength_calibration.py
aspired/extinction/cp_atm_extinct.txt
aspired/extinction/ct_atm_extinct.txt
aspired/extinction/kp_atm_extinct.txt
aspired/extinction/ls_atm_extinct.txt
aspired/extinction/mk_atm_extinct.txt
aspired/extinction/orm_atm_extinct.txt
aspired/standards/designation_to_lib_filename.json
aspired/standards/designation_to_position.json
aspired/standards/esoctiostan-filename-to-identifier.json
aspired/standards/esohststan-filename-to-identifier.json
aspired/standards/esookestan-filename-to-identifier.json
aspired/standards/esowdstan-filename-to-identifier.json
aspired/standards/esoxshooter-filename-to-identifier.json
aspired/standards/filename_to_lib.json
aspired/standards/generate_dictionary.py
aspired/standards/get_designations.py
aspired/standards/ingfg-filename-to-identifier.json
aspired/standards/ingmas-filename-to-identifier.json
aspired/standards/ingog-filename-to-identifier.json
aspired/standards/ingoke-filename-to-identifier.json
aspired/standards/ingsto-filename-to-identifier.json
aspired/standards/irafblackbody-filename-to-identifier.json
aspired/standards/irafbstdscal-filename-to-identifier.json
aspired/standards/irafctiocal-filename-to-identifier.json
aspired/standards/irafctionewcal-filename-to-identifier.json
aspired/standards/irafiidscal-filename-to-identifier.json
aspired/standards/irafirscal-filename-to-identifier.json
aspired/standards/irafoke1990-filename-to-identifier.json
aspired/standards/irafredcal-filename-to-identifier.json
aspired/standards/irafspec16cal-filename-to-identifier.json
aspired/standards/irafspec50cal-filename-to-identifier.json
aspired/standards/irafspechayescal-filename-to-identifier.json
aspired-0.5.1.dist-info/LICENSE
aspired-0.5.1.dist-info/METADATA
aspired-0.5.1.dist-info/WHEEL
aspired-0.5.1.dist-info/top_level.txt
aspired-0.5.1.dist-info/RECORD
