Metadata-Version: 2.1
Name: aspired
Version: 0.5.1
Summary: The iraf-free spectral data reduction toolkit.
Home-page: https://aspired.readthedocs.io/en/latest/?badge=latest
Author: Marco C Lam, Robert J Smith
Author-email: lam@mail.tau.ac.il, r.j.smith@ljmu.ac.uk
Maintainer: Marco C Lam
Maintainer-email: lam@mail.tau.ac.il
License: BSD-3-Clause
Download-URL: https://github.com/cylammarco/aspired
Platform: UNKNOWN
Classifier: License :: OSI Approved :: BSD License
Classifier: Programming Language :: Python :: 3
Classifier: Programming Language :: Python :: 3.7
Classifier: Programming Language :: Python :: 3.8
Classifier: Programming Language :: Python :: 3.9
Classifier: Programming Language :: Python :: 3.10
Classifier: Programming Language :: Python :: 3.11
Classifier: Operating System :: OS Independent
Requires-Python: >=3.6
Requires-Dist: astropy (>=4.3)
Requires-Dist: numpy (>=1.18)
Requires-Dist: scipy (>=1.7)
Requires-Dist: plotly (>=5.6)
Requires-Dist: kaleido (>=0.2)
Requires-Dist: astroscrappy (>=1.1)
Requires-Dist: ccdproc (!=2.4.0,>=2.3)
Requires-Dist: statsmodels (>=0.13)
Requires-Dist: spectresc (>=1.0.1)
Requires-Dist: specutils (>=1.8)
Requires-Dist: rascal (<0.4)
